multi_prophet/__init__.py
multi_prophet/data_builder.py
multi_prophet/factories.py
multi_prophet/plots.py
multi_prophet/prophet.py
multi_prophet-1.1.1.dist-info/METADATA
multi_prophet-1.1.1.dist-info/WHEEL
multi_prophet-1.1.1.dist-info/top_level.txt
multi_prophet-1.1.1.dist-info/RECORD
