Metadata-Version: 2.1
Name: multi-prophet
Version: 1.1.1
Summary: Multivariate forecasting using Facebook Prophet
Home-page: https://github.com/vonum/multi-prophet
Author: Milan Keca
Author-email: vonum.mk@gmail.com
License: UNKNOWN
Platform: UNKNOWN
Classifier: Programming Language :: Python :: 3
Classifier: License :: OSI Approved :: MIT License
Classifier: Operating System :: OS Independent
Requires-Dist: prophet (==1.0)
Requires-Dist: pandas
Requires-Dist: plotly
